barinbar/__init__.py
barinbar/plot.py
barinbar/plot_old.py
barinbar-0.2.0.dist-info/LICENSE
barinbar-0.2.0.dist-info/METADATA
barinbar-0.2.0.dist-info/WHEEL
barinbar-0.2.0.dist-info/RECORD
