Metadata-Version: 2.3
Name: barinbar
Version: 0.2.0
Summary: Generate a cool bar in bar chart
License: MIT
Author: Daniel Vecera
Author-email: daniel.vecera@outlook.com
Requires-Python: >=3.10.0
Classifier: License :: OSI Approved :: MIT License
Classifier: Programming Language :: Python :: 3
Classifier: Programming Language :: Python :: 3.10
Classifier: Programming Language :: Python :: 3.11
Classifier: Programming Language :: Python :: 3.12
Classifier: Programming Language :: Python :: 3.13
Requires-Dist: matplotlib
Requires-Dist: numpy
Requires-Dist: pandas
Requires-Dist: squarify
